fastasyncapi/__init__.py
fastasyncapi-0.1.dist-info/LICENSE
fastasyncapi-0.1.dist-info/WHEEL
fastasyncapi-0.1.dist-info/METADATA
fastasyncapi-0.1.dist-info/RECORD
