Metadata-Version: 2.1
Name: fastasyncapi
Version: 0.1
Summary: Python FastAsyncApi project!
Author-email: Mohsen Mahmoodi <m.mahmoodi.biz@gmail.com>
Classifier: License :: OSI Approved :: MIT License
Project-URL: Home, https://fastasyncapi.github.io
